userlog/__init__.py
userlog/admin.py
userlog/apps.py
userlog/middleware.py
userlog/models.py
userlog/urls.py
userlog/views.py
django_soc-0.3.dist-info/METADATA
django_soc-0.3.dist-info/WHEEL
django_soc-0.3.dist-info/top_level.txt
django_soc-0.3.dist-info/RECORD
